epikit/__init__.py
epikit/check.py
epikit/core.py
epikit/generate.py
epikit/ensemble/__init__.py
epikit/process/__init__.py
epikit/workflow/__init__.py
epikit-0.6.7.dist-info/METADATA
epikit-0.6.7.dist-info/WHEEL
epikit-0.6.7.dist-info/entry_points.txt
epikit-0.6.7.dist-info/top_level.txt
epikit-0.6.7.dist-info/RECORD
