Metadata-Version: 2.4
Name: epikit
Version: 0.6.7
Summary: epigenetics toolkit
Author-email: "David H. Rogers" <dhr@lanl.gov>
Requires-Dist: pyyaml
